ChangeLog
MANIFEST.in
README.rst
setup.py
livelex/__init__.py
livelex/action.py
livelex/document.py
livelex/language.py
livelex/lexicon.py
livelex/pattern.py
livelex/pkginfo.py
livelex/query.py
livelex/regex.py
livelex/target.py
livelex/tree.py
livelex/treebuilder.py
livelex/treedocument.py
livelex/util.py
livelex/validate.py
livelex.egg-info/PKG-INFO
livelex.egg-info/SOURCES.txt
livelex.egg-info/dependency_links.txt
livelex.egg-info/top_level.txt
livelex/lang/__init__.py
livelex/lang/lilypond.py
livelex/lang/lilypond_words.py
livelex/lang/scheme.py
livelex/lang/scheme_words.py
livelex/lang/xml.py